README.md
setup.cfg
setup.py
saj_distributions/Binomialdistribution.py
saj_distributions/Gaussiandistribution.py
saj_distributions/Generaldistribution.py
saj_distributions/__init__.py
saj_distributions.egg-info/PKG-INFO
saj_distributions.egg-info/SOURCES.txt
saj_distributions.egg-info/dependency_links.txt
saj_distributions.egg-info/not-zip-safe
saj_distributions.egg-info/top_level.txt