Metadata-Version: 1.0
Name: saj-distributions
Version: 0.1
Summary: Gaussian distributions
Home-page: UNKNOWN
Author: sajanraj
Author-email: sajanraj.t.d@gmail.com
License: UNKNOWN
Platform: UNKNOWN
